Metadata-Version: 2.4
Name: Soprano
Version: 0.10.2
Summary: A Python library to crack crystals
Project-URL: Homepage, https://ccp-nc.github.io/soprano/
Author-email: Simone Sturniolo <simone.sturniolo@stfc.ac.uk>, "J. Kane Shenton" <kane.shenton@stfc.ac.uk>
License-Expression: LGPL-3.0-or-later
License-File: LICENSE.txt
Keywords: ccpnc,computational chemistry,crystallography
Classifier: Development Status :: 4 - Beta
Classifier: Intended Audience :: Science/Research
Classifier: License :: OSI Approved :: GNU Library or Lesser General Public License (LGPL)
Classifier: Programming Language :: Python :: 3
Classifier: Programming Language :: Python :: 3 :: Only
Classifier: Programming Language :: Python :: 3.10
Classifier: Programming Language :: Python :: 3.11
Classifier: Programming Language :: Python :: 3.12
Classifier: Programming Language :: Python :: 3.13
Classifier: Topic :: Scientific/Engineering :: Chemistry
Classifier: Topic :: Scientific/Engineering :: Information Analysis
Classifier: Topic :: Scientific/Engineering :: Physics
Requires-Python: >=3.10
Requires-Dist: adjusttext
Requires-Dist: ase>=3.26
Requires-Dist: bottleneck>=1.3.6
Requires-Dist: click-log
Requires-Dist: click<8.3,>=8.2.1
Requires-Dist: matplotlib
Requires-Dist: numpy>=1.18.5
Requires-Dist: pandas>=2.0
Requires-Dist: pydantic>=2.0
Requires-Dist: scipy
Requires-Dist: spglib>=2.4
Provides-Extra: dev
Requires-Dist: black; extra == 'dev'
Requires-Dist: flake8; extra == 'dev'
Requires-Dist: pre-commit; extra == 'dev'
Requires-Dist: pytest; extra == 'dev'
Requires-Dist: pytest-cov; extra == 'dev'
Provides-Extra: docs
Requires-Dist: jupyter-book~=1.0.2; extra == 'docs'
Requires-Dist: sphinx-click; extra == 'docs'
Requires-Dist: sphinxcontrib-bibtex; extra == 'docs'
Requires-Dist: sphinxcontrib-mermaid; extra == 'docs'
Provides-Extra: legacy
Requires-Dist: numpy<2.0,>=1.26.0; extra == 'legacy'
